sdaab
