Metadata-Version: 2.1
Name: sdaab
Version: 1.0.2
Summary: Simple Data Abstraction to access different types of storages.
Home-page: https://github.com/ngshya/sdaab
Author: ngshya
Author-email: ngshya@gmail.com
License: GPLv3
Platform: UNKNOWN
